datasette_configure_fts/__init__.py
datasette_configure_fts/templates/configure_fts_database.html
datasette_configure_fts/templates/configure_fts_index.html
datasette_configure_fts-1.1.4.dist-info/LICENSE
datasette_configure_fts-1.1.4.dist-info/METADATA
datasette_configure_fts-1.1.4.dist-info/WHEEL
datasette_configure_fts-1.1.4.dist-info/entry_points.txt
datasette_configure_fts-1.1.4.dist-info/top_level.txt
datasette_configure_fts-1.1.4.dist-info/RECORD
