Metadata-Version: 2.1
Name: datasette-configure-fts
Version: 1.1.4
Summary: Datasette plugin for enabling full-text search against selected table columns
Home-page: https://github.com/simonw/datasette-configure-fts
Author: Simon Willison
License: Apache License, Version 2.0
License-File: LICENSE
Requires-Dist: datasette >=0.51
Requires-Dist: sqlite-utils >=2.10
Provides-Extra: test
Requires-Dist: pytest ; extra == 'test'
Requires-Dist: pytest-asyncio ; extra == 'test'
Requires-Dist: httpx ; extra == 'test'
